Face_Anti_Spoofing/__init__.py
Face_Anti_Spoofing/inference_onnx.py
FAS_FT_gpu-2.1.dist-info/LICENSE
FAS_FT_gpu-2.1.dist-info/METADATA
FAS_FT_gpu-2.1.dist-info/WHEEL
FAS_FT_gpu-2.1.dist-info/top_level.txt
FAS_FT_gpu-2.1.dist-info/RECORD
