Metadata-Version: 2.1
Name: FAS-FT-gpu
Version: 2.1
Home-page: https://gitlab.ftech.ai/computer-vision/research/face-anti-spoofing.git
Author: Thong Le
Author-email: thonglv@ftech.ai
Classifier: Programming Language :: Python :: 3
Classifier: License :: OSI Approved :: MIT License
Classifier: Operating System :: OS Independent
Requires-Python: >=3.6
License-File: LICENSE
Requires-Dist: onnxruntime-gpu
